syft/VERSION
syft/__init__.py
syft/__main__.py
syft/abstract_server.py
syft/deployment_type.py
syft/orchestra.py
syft/stable_version.py
syft/assets/css/fonts.css
syft/assets/css/style.css
syft/assets/css/tabulator_pysyft.min.css
syft/assets/img/logo.png
syft/assets/img/small-syft-symbol-logo.png
syft/assets/jinja/syft_exception.jinja2
syft/assets/jinja/table.jinja2
syft/assets/js/table.js
syft/assets/js/tabulator.min.js
syft/assets/svg/arrow.svg
syft/assets/svg/clipboard.svg
syft/assets/svg/copy.svg
syft/assets/svg/folder.svg
syft/assets/svg/info.svg
syft/assets/svg/request.svg
syft/assets/svg/search.svg
syft/assets/svg/table.svg
syft/capnp/__init__.py
syft/capnp/iterable.capnp
syft/capnp/kv_iterable.capnp
syft/capnp/recursive_serde.capnp
syft/client/__init__.py
syft/client/api.py
syft/client/client.py
syft/client/connection.py
syft/client/datasite_client.py
syft/client/enclave_client.py
syft/client/errors.py
syft/client/gateway_client.py
syft/client/protocol.py
syft/client/registry.py
syft/client/search.py
syft/client/sync_decision.py
syft/client/syncing.py
syft/client/user_settings.py
syft/custom_worker/__init__.py
syft/custom_worker/builder.py
syft/custom_worker/builder_docker.py
syft/custom_worker/builder_k8s.py
syft/custom_worker/builder_types.py
syft/custom_worker/config.py
syft/custom_worker/k8s.py
syft/custom_worker/runner_k8s.py
syft/custom_worker/utils.py
syft/custom_worker/workerpool_upgrade_utils.py
syft/dev/__init__.py
syft/dev/prof.py
syft/protocol/data_protocol.py
syft/protocol/protocol_version.json
syft/protocol/releases/.empty
syft/protocol/releases/.gitignore
syft/protocol/releases/0.9.1.json
syft/protocol/releases/0.9.2.json
syft/serde/__init__.py
syft/serde/array.py
syft/serde/arrow.py
syft/serde/capnp.py
syft/serde/deserialize.py
syft/serde/json_serde.py
syft/serde/lib_permissions.py
syft/serde/lib_service_registry.py
syft/serde/mock.py
syft/serde/recursive.py
syft/serde/recursive_primitives.py
syft/serde/serializable.py
syft/serde/serialize.py
syft-0.9.2.dist-info/LICENSE
syft-0.9.2.dist-info/METADATA
syft-0.9.2.dist-info/WHEEL
syft-0.9.2.dist-info/entry_points.txt
syft-0.9.2.dist-info/top_level.txt
syft-0.9.2.dist-info/RECORD
