Metadata-Version: 2.1
Name: syft
Version: 0.9.2
Summary: Perform numpy-like analysis on data that remains in someone elses server
Home-page: https://docs.openmined.org
Author: OpenMined
Author-email: info@openmined.org
License: Apache-2.0
Project-URL: Source, https://github.com/OpenMined/PySyft
Project-URL: Tracker, https://github.com/OpenMined/PySyft/issues
Platform: any
Classifier: Development Status :: 4 - Beta
Classifier: Programming Language :: Python
Requires-Python: >=3.10
License-File: LICENSE
Requires-Dist: setuptools
Requires-Dist: bcrypt==4.1.2
Requires-Dist: boto3==1.34.56
Requires-Dist: forbiddenfruit==0.1.4
Requires-Dist: packaging>=23.0
Requires-Dist: pyarrow==17.0.0
Requires-Dist: pycapnp==2.0.0
Requires-Dist: pydantic[email]==2.6.0
Requires-Dist: pydantic-settings==2.2.1
Requires-Dist: pynacl==1.5.0
Requires-Dist: pyzmq<=25.1.1,>=23.2.1
Requires-Dist: requests==2.32.3
Requires-Dist: RestrictedPython==7.0
Requires-Dist: tqdm==4.66.4
Requires-Dist: typeguard==4.1.5
Requires-Dist: typing-extensions==4.12.0
Requires-Dist: sherlock[filelock]==0.4.1
Requires-Dist: uvicorn[standard]==0.30.0
Requires-Dist: markdown==3.5.2
Requires-Dist: fastapi==0.111.0
Requires-Dist: psutil==6.0.0
Requires-Dist: itables==1.7.1
Requires-Dist: argon2-cffi==23.1.0
Requires-Dist: matplotlib<3.9.1,>=3.7.1
Requires-Dist: pandas==2.2.2
Requires-Dist: docker==7.1.0
Requires-Dist: kr8s==0.13.5
Requires-Dist: PyYAML==6.0.1
Requires-Dist: azure-storage-blob==12.19.1
Requires-Dist: ipywidgets==8.1.2
Requires-Dist: tomli==2.0.1
Requires-Dist: tomli-w==1.0.0
Requires-Dist: rich==13.7.1
Requires-Dist: jinja2==3.1.4
Requires-Dist: tenacity==8.3.0
Requires-Dist: nh3==0.2.17
Requires-Dist: psycopg[binary]==3.1.19
Requires-Dist: psycopg[pool]==3.1.19
Requires-Dist: ipython<8.27.0
Requires-Dist: dynaconf==3.2.6
Requires-Dist: sqlalchemy==2.0.32
Requires-Dist: psycopg2-binary==2.9.9
Requires-Dist: numpy<=1.24.4,>=1.23.5; python_version < "3.12"
Requires-Dist: numpy<1.27,>=1.26.4; python_version >= "3.12"
Provides-Extra: data_science
Requires-Dist: transformers==4.41.2; extra == "data-science"
Requires-Dist: opendp==0.9.2; extra == "data-science"
Requires-Dist: evaluate==0.4.2; extra == "data-science"
Requires-Dist: recordlinkage==0.16; extra == "data-science"
Requires-Dist: torch==2.2.2; extra == "data-science"
Provides-Extra: dev
Requires-Dist: pytest<8; extra == "dev"
Requires-Dist: pytest-cov; extra == "dev"
Requires-Dist: pytest-xdist[psutil]; extra == "dev"
Requires-Dist: pytest-parallel; extra == "dev"
Requires-Dist: pytest-randomly; extra == "dev"
Requires-Dist: pytest-sugar; extra == "dev"
Requires-Dist: pytest-lazy-fixture; extra == "dev"
Requires-Dist: pytest-rerunfailures; extra == "dev"
Requires-Dist: coverage; extra == "dev"
Requires-Dist: faker; extra == "dev"
Requires-Dist: distro; extra == "dev"
Requires-Dist: dynaconf; extra == "dev"
Requires-Dist: pytest-asyncio; extra == "dev"
Requires-Dist: pytest-timeout; extra == "dev"
Requires-Dist: anyio; extra == "dev"
Requires-Dist: opentelemetry-api==1.27.0; extra == "dev"
Requires-Dist: opentelemetry-sdk==1.27.0; extra == "dev"
Requires-Dist: opentelemetry-exporter-otlp==1.27.0; extra == "dev"
Requires-Dist: opentelemetry-instrumentation==0.48b0; extra == "dev"
Requires-Dist: opentelemetry-instrumentation-requests==0.48b0; extra == "dev"
Requires-Dist: opentelemetry-instrumentation-fastapi==0.48b0; extra == "dev"
Requires-Dist: opentelemetry-instrumentation-botocore==0.48b0; extra == "dev"
Requires-Dist: opentelemetry-instrumentation-logging==0.48b0; extra == "dev"
Requires-Dist: opentelemetry-instrumentation-sqlalchemy==0.48b0; extra == "dev"
Requires-Dist: opentelemetry-instrumentation-threading==0.48b0; extra == "dev"
Requires-Dist: bandit==1.7.8; extra == "dev"
Requires-Dist: debugpy==1.8.2; extra == "dev"
Requires-Dist: importlib-metadata==7.1.0; extra == "dev"
Requires-Dist: isort==5.13.2; extra == "dev"
Requires-Dist: mypy==1.10.0; extra == "dev"
Requires-Dist: pre-commit==3.7.1; extra == "dev"
Requires-Dist: ruff==0.4.7; extra == "dev"
Requires-Dist: safety>=2.4.0b2; extra == "dev"
Requires-Dist: aiosmtpd==1.4.6; extra == "dev"
Provides-Extra: telemetry
Requires-Dist: opentelemetry-api==1.27.0; extra == "telemetry"
Requires-Dist: opentelemetry-sdk==1.27.0; extra == "telemetry"
Requires-Dist: opentelemetry-exporter-otlp==1.27.0; extra == "telemetry"
Requires-Dist: opentelemetry-instrumentation==0.48b0; extra == "telemetry"
Requires-Dist: opentelemetry-instrumentation-requests==0.48b0; extra == "telemetry"
Requires-Dist: opentelemetry-instrumentation-fastapi==0.48b0; extra == "telemetry"
Requires-Dist: opentelemetry-instrumentation-botocore==0.48b0; extra == "telemetry"
Requires-Dist: opentelemetry-instrumentation-logging==0.48b0; extra == "telemetry"
Requires-Dist: opentelemetry-instrumentation-sqlalchemy==0.48b0; extra == "telemetry"
Requires-Dist: opentelemetry-instrumentation-threading==0.48b0; extra == "telemetry"
Provides-Extra: test_plugins
Requires-Dist: pytest<8; extra == "test-plugins"
Requires-Dist: pytest-cov; extra == "test-plugins"
Requires-Dist: pytest-xdist[psutil]; extra == "test-plugins"
Requires-Dist: pytest-parallel; extra == "test-plugins"
Requires-Dist: pytest-randomly; extra == "test-plugins"
Requires-Dist: pytest-sugar; extra == "test-plugins"
Requires-Dist: pytest-lazy-fixture; extra == "test-plugins"
Requires-Dist: pytest-rerunfailures; extra == "test-plugins"
Requires-Dist: coverage; extra == "test-plugins"
Requires-Dist: faker; extra == "test-plugins"
Requires-Dist: distro; extra == "test-plugins"
Requires-Dist: dynaconf; extra == "test-plugins"
Requires-Dist: pytest-asyncio; extra == "test-plugins"
Requires-Dist: pytest-timeout; extra == "test-plugins"
Requires-Dist: anyio; extra == "test-plugins"
